{
  "main": {
    "id": "6a32516d7a518ad6",
    "type": "split",
    "children": [
      {
        "id": "a210f5afb7858826",
        "type": "tabs",
        "children": [
          {
            "id": "336143b332468e30",
            "type": "leaf",
            "state": {
              "type": "markdown",
              "state": {
                "file": "Design Patterns/Head First Design Pattern Book.md",
                "mode": "source",
                "source": false
              }
            }
          }
        ]
      }
    ],
    "direction": "vertical"
  },
  "left": {
    "id": "ccd25ecf682ce10b",
    "type": "split",
    "children": [
      {
        "id": "711324095df0b2a7",
        "type": "tabs",
        "children": [
          {
            "id": "6d53016e3bb1922b",
            "type": "leaf",
            "state": {
              "type": "file-explorer",
              "state": {
                "sortOrder": "alphabetical"
              }
            }
          },
          {
            "id": "98e0e33a823f8a83",
            "type": "leaf",
            "state": {
              "type": "search",
              "state": {
                "query": "",
                "matchingCase": false,
                "explainSearch": false,
                "collapseAll": false,
                "extraContext": false,
                "sortOrder": "alphabetical"
              }
            }
          },
          {
            "id": "2f972cd74a312ee8",
            "type": "leaf",
            "state": {
              "type": "bookmarks",
              "state": {}
            }
          }
        ]
      }
    ],
    "direction": "horizontal",
    "width": 300
  },
  "right": {
    "id": "fefc1e2e8c4c43ba",
    "type": "split",
    "children": [
      {
        "id": "fe255d1ef5128856",
        "type": "tabs",
        "children": [
          {
            "id": "79862e503a9080b3",
            "type": "leaf",
            "state": {
              "type": "backlink",
              "state": {
                "file": "Design Patterns/Head First Design Pattern Book.md",
                "collapseAll": false,
                "extraContext": false,
                "sortOrder": "alphabetical",
                "showSearch": false,
                "searchQuery": "",
                "backlinkCollapsed": false,
                "unlinkedCollapsed": true
              }
            }
          },
          {
            "id": "ba0a7c3c8389ae07",
            "type": "leaf",
            "state": {
              "type": "outgoing-link",
              "state": {
                "file": "Design Patterns/Head First Design Pattern Book.md",
                "linksCollapsed": false,
                "unlinkedCollapsed": true
              }
            }
          },
          {
            "id": "caca3fc23d30216d",
            "type": "leaf",
            "state": {
              "type": "tag",
              "state": {
                "sortOrder": "frequency",
                "useHierarchy": true
              }
            }
          },
          {
            "id": "cc7cd217d3be004d",
            "type": "leaf",
            "state": {
              "type": "outline",
              "state": {
                "file": "Design Patterns/Head First Design Pattern Book.md"
              }
            }
          }
        ]
      }
    ],
    "direction": "horizontal",
    "width": 300,
    "collapsed": true
  },
  "left-ribbon": {
    "hiddenItems": {
      "switcher:Open quick switcher": false,
      "graph:Open graph view": false,
      "canvas:Create new canvas": false,
      "daily-notes:Open today's daily note": false,
      "templates:Insert template": false,
      "command-palette:Open command palette": false
    }
  },
  "active": "336143b332468e30",
  "lastOpenFiles": [
    "Pasted image 20240220144822.png",
    "Pasted image 20240220144758.png",
    "Pasted image 20240220144742.png",
    "Pasted image 20240220164402.png",
    "Pasted image 20240220164336.png",
    "Pasted image 20240220164305.png",
    "Pasted image 20240220164151.png",
    "Pasted image 20240220162630.png",
    "Database/General-Notes-SQL.md",
    "Images/PolyMorePhism.png",
    "Images/Pasted image 20240217155047.png",
    "Database/Fundamentals of Database System.md",
    "Images/Pasted image 20240217164629.png",
    "Design Patterns/Head First Design Pattern Book.md",
    "Database/WAL.md",
    "Deep Learning/CNN Notes.md",
    "Machine Learning/PCA.md",
    "Database/Redis.md",
    "Machine Learning",
    "Untitled.md",
    "Database",
    "Welcome.md",
    "create a link.md"
  ]
}